{
 "bowl": {
  "main": {
   "modId": "_sys/root",
   "fields": {
    "main": [
     {
      "modId": "PlainHTMLElements:PlainHTML/image",
      "fields": {
       "href": "",
       "image_src": {
        "resKey": "230d872f9a223d0f7d354142e4526063",
        "path": "./index_files/resources/no_image.jpg",
        "resType": "",
        "webUrl": ""
       },
       "alt_text": ""
      },
      "anchor": "",
      "dec": ""
     },
     {
      "modId": "PlainHTMLElements:PlainHTML/MultiText",
      "fields": {
       "main": {
        "src": "## 画像を読み込む場合にはimgタグに以下のように記述します。",
        "editor": "markdown"
       }
      },
      "anchor": "",
      "dec": ""
     },
     {
      "modId": "PlainHTMLElements:PlainHTML/MultiText",
      "fields": {
       "main": {
        "src": "<h2><div class=\"sourceview\">\n<pre class=\"brush: html;\">\n&lt;img src=&quot;&lt;?= htmlspecialchars($theme-&gt;files(&#039;/images/ファイル名&#039;)); ?&gt;&quot;&gt;\n</pre>\n</div></h2>",
        "editor": ""
       }
      },
      "anchor": "",
      "dec": ""
     },
     {
      "modId": "PlainHTMLElements:PlainHTML/MultiText",
      "fields": {
       "main": {
        "src": "## 画像ファイルを置く場所は「<font color=\"#d14\">px-files &gt; themes &gt; pickles2 &gt; theme_files &gt; images</font>」となります。",
        "editor": "markdown"
       }
      },
      "anchor": "",
      "dec": ""
     },
     {
      "modId": "PlainHTMLElements:PlainHTML/MultiText",
      "fields": {
       "main": {
        "src": "## レイアウトファイルとの相対関係でHTMLとして出力される際には「&lt;img src=&quot;/theme_files/images/ファイル名&quot;&gt;」となりそうですが、実際には「&lt;img src=&quot;/common/px_resources/p/theme/pickles2/images/ファイル名&quot;&gt;」と出力されますので覚えておくと良いでしょう。",
        "editor": "markdown"
       }
      },
      "anchor": "",
      "dec": ""
     },
     {
      "modId": "PlainHTMLElements:PlainHTML/MultiText",
      "fields": {
       "main": {
        "src": "## では実際にやってみてうまくいったら次のチャプターに進みましょう。次の章ではPHPの置き換えに挑戦していきましょう。",
        "editor": "markdown"
       }
      },
      "anchor": "",
      "dec": ""
     }
    ]
   }
  }
 }
}